MANIFEST.in
README.txt
setup.py
docs/HISTORY.txt
docs/LICENSE.txt
src/silva/__init__.py
src/silva.core.conf.egg-info/PKG-INFO
src/silva.core.conf.egg-info/SOURCES.txt
src/silva.core.conf.egg-info/dependency_links.txt
src/silva.core.conf.egg-info/namespace_packages.txt
src/silva.core.conf.egg-info/not-zip-safe
src/silva.core.conf.egg-info/requires.txt
src/silva.core.conf.egg-info/top_level.txt
src/silva/core/__init__.py
src/silva/core/conf/__init__.py
src/silva/core/conf/configure.zcml
src/silva/core/conf/installer.py
src/silva/core/conf/interfaces.py
src/silva/core/conf/meta.zcml
src/silva/core/conf/schema.py
src/silva/core/conf/utils.py
src/silva/core/conf/martiansupport/__init__.py
src/silva/core/conf/martiansupport/content.py
src/silva/core/conf/martiansupport/directives.py
src/silva/core/conf/martiansupport/extension.py
src/silva/core/conf/martiansupport/interfaces.py
src/silva/core/conf/martiansupport/service.py
src/silva/core/conf/martiansupport/utils.py