Metadata-Version: 1.1
Name: silva.core.conf
Version: 3.0.3
Summary: Configuration machinery for Silva CMS
Home-page: https://github.com/silvacms/silva.core.conf
Author: Infrae
Author-email: info@infrae.com
License: BSD
Keywords: silva core configuration
Platform: UNKNOWN
Classifier: Framework :: Zope2
Classifier: License :: OSI Approved :: BSD License
Classifier: Programming Language :: Python
Classifier: Topic :: Software Development :: Libraries :: Python Modules
